iops_profiler/__init__.py
iops_profiler/_version.py
iops_profiler/collector.py
iops_profiler/display.py
iops_profiler/magic.py
iops_profiler-0.2.0.dist-info/licenses/LICENSE
iops_profiler-0.2.0.dist-info/METADATA
iops_profiler-0.2.0.dist-info/WHEEL
iops_profiler-0.2.0.dist-info/top_level.txt
iops_profiler-0.2.0.dist-info/RECORD
