Metadata-Version: 2.4
Name: iops-profiler
Version: 0.2.0
Summary: Jupyter magic for measuring I/O operations per second
Author-email: LINCC Frameworks <lincc-frameworks-team@lists.lsst.org>
License: MIT
Project-URL: Homepage, https://github.com/lincc-frameworks/iops-profiler
Project-URL: Repository, https://github.com/lincc-frameworks/iops-profiler
Project-URL: Source Code, https://github.com/lincc-frameworks/iops-profiler
Classifier: Development Status :: 4 - Beta
Classifier: Intended Audience :: Developers
Classifier: Intended Audience :: Science/Research
Classifier: Operating System :: OS Independent
Classifier: Programming Language :: Python
Classifier: Programming Language :: Python :: 3
Classifier: Programming Language :: Python :: 3.10
Classifier: Programming Language :: Python :: 3.11
Classifier: Programming Language :: Python :: 3.12
Classifier: Programming Language :: Python :: 3.13
Classifier: Framework :: IPython
Classifier: Framework :: Jupyter
Requires-Python: >=3.10
License-File: LICENSE
Requires-Dist: ipython
Requires-Dist: psutil
Requires-Dist: matplotlib
Requires-Dist: numpy
Provides-Extra: dev
Requires-Dist: jupyter; extra == "dev"
Requires-Dist: pre-commit; extra == "dev"
Requires-Dist: pytest; extra == "dev"
Requires-Dist: pytest-cov; extra == "dev"
Requires-Dist: ruff; extra == "dev"
Dynamic: license-file
